PFASProphet/.gitignore
PFASProphet/__init__.py
PFASProphet/cli.py
PFASProphet/commons.py
PFASProphet/model.model
PFASProphet/predictor.py
pfasprophet-0.1.0.dist-info/METADATA
pfasprophet-0.1.0.dist-info/WHEEL
pfasprophet-0.1.0.dist-info/entry_points.txt
pfasprophet-0.1.0.dist-info/licenses/LICENSE
pfasprophet-0.1.0.dist-info/RECORD
