Metadata-Version: 2.4
Name: PFASProphet
Version: 0.1.0
Summary: ML-based PFAS prediction from mass spectrometry data
Author-email: Mathieu Feraud <Mathieu.Feraud@outlook.com>
License: MIT
License-File: LICENSE
Classifier: License :: OSI Approved :: MIT License
Classifier: Operating System :: OS Independent
Classifier: Programming Language :: Python :: 3
Requires-Python: <3.13,>=3.12
Requires-Dist: joblib==1.5.3
Requires-Dist: lightgbm==4.6.0
Requires-Dist: numpy==2.4.1
Requires-Dist: pandas==2.3.3
Requires-Dist: pydantic==2.12.5
Requires-Dist: scikit-learn==1.4.2
Provides-Extra: test
Requires-Dist: pytest>=8.0.0; extra == 'test'
